PythonOpencv3JisuanjiShijueMijiChuyi/README.md
PythonOpencv3JisuanjiShijueMijiChuyi/__init__.py
PythonOpencv3JisuanjiShijueMijiChuyi/__main__.py
PythonOpencv3JisuanjiShijueMijiChuyi/file.epub
PythonOpencv3JisuanjiShijueMijiChuyi/index.html
PythonOpencv3JisuanjiShijueMijiChuyi/css/__init__.py
PythonOpencv3JisuanjiShijueMijiChuyi/css/annotations.css
PythonOpencv3JisuanjiShijueMijiChuyi/css/main.css
PythonOpencv3JisuanjiShijueMijiChuyi/css/normalize.css
PythonOpencv3JisuanjiShijueMijiChuyi/css/popup.css
PythonOpencv3JisuanjiShijueMijiChuyi/font/__init__.py
PythonOpencv3JisuanjiShijueMijiChuyi/font/fontello.eot
PythonOpencv3JisuanjiShijueMijiChuyi/font/fontello.svg
PythonOpencv3JisuanjiShijueMijiChuyi/font/fontello.ttf
PythonOpencv3JisuanjiShijueMijiChuyi/font/fontello.woff
PythonOpencv3JisuanjiShijueMijiChuyi/img/__init__.py
PythonOpencv3JisuanjiShijueMijiChuyi/img/annotator-glyph-sprite.png
PythonOpencv3JisuanjiShijueMijiChuyi/img/annotator-icon-sprite.png
PythonOpencv3JisuanjiShijueMijiChuyi/img/apple-touch-icon.png
PythonOpencv3JisuanjiShijueMijiChuyi/img/cancelfullscreen.png
PythonOpencv3JisuanjiShijueMijiChuyi/img/close.png
PythonOpencv3JisuanjiShijueMijiChuyi/img/fullscreen.png
PythonOpencv3JisuanjiShijueMijiChuyi/img/loader.gif
PythonOpencv3JisuanjiShijueMijiChuyi/img/menu-icon.png
PythonOpencv3JisuanjiShijueMijiChuyi/img/save.png
PythonOpencv3JisuanjiShijueMijiChuyi/img/saved.png
PythonOpencv3JisuanjiShijueMijiChuyi/img/settings-s.png
PythonOpencv3JisuanjiShijueMijiChuyi/img/settings.png
PythonOpencv3JisuanjiShijueMijiChuyi/img/star.png
PythonOpencv3JisuanjiShijueMijiChuyi/js/__init__.py
PythonOpencv3JisuanjiShijueMijiChuyi/js/epub.js
PythonOpencv3JisuanjiShijueMijiChuyi/js/epub.min.js
PythonOpencv3JisuanjiShijueMijiChuyi/js/epub.min.map
PythonOpencv3JisuanjiShijueMijiChuyi/js/hooks.min.js
PythonOpencv3JisuanjiShijueMijiChuyi/js/hooks.min.map
PythonOpencv3JisuanjiShijueMijiChuyi/js/reader.js
PythonOpencv3JisuanjiShijueMijiChuyi/js/reader.js.map
python_opencv3_jisuanji_shijue_miji_chuyi-2024.3.6.0.dist-info/METADATA
python_opencv3_jisuanji_shijue_miji_chuyi-2024.3.6.0.dist-info/WHEEL
python_opencv3_jisuanji_shijue_miji_chuyi-2024.3.6.0.dist-info/entry_points.txt
python_opencv3_jisuanji_shijue_miji_chuyi-2024.3.6.0.dist-info/top_level.txt
python_opencv3_jisuanji_shijue_miji_chuyi-2024.3.6.0.dist-info/RECORD
